Vys/__init__.py
Vys/app/__init__.py
Vys/app/VysTime/__init__.py
Vys/app/connectors/Api.py
Vys/app/connectors/__init__.py
Vys/app/core/__init__.py
Vys/app/core/connectors.py
Vys/app/core/datetime_apps.py
Vys/app/core/db.py
Vys/app/core/excel_core.py
Vys/app/core/fs.py
Vys/app/errors/__init__.py
Vys/app/excel/__init__.py
Vys/app/excel/excel_file.py
Vys/app/models/__init__.py
Vys/app/models/schema.py
Vys/app/struct/__init__.py
Vys/app/struct/connector.py
Vys/app/struct/errors.py
Vys/app/struct/excel.py
Vys/app/struct/models.py
Vys/app/struct/vystime.py
Vys/config/__init__.py
Vys-0.2.2.dist-info/LICENSE
Vys-0.2.2.dist-info/METADATA
Vys-0.2.2.dist-info/WHEEL
Vys-0.2.2.dist-info/top_level.txt
Vys-0.2.2.dist-info/RECORD
