Metadata-Version: 2.1
Name: Vys
Version: 0.2.2
Summary: A collection of classes that allow for easier usage of common packages. 
Home-page: http://www.connorwhite.uk
Author: Connor White
Author-email: connorwhite101@gmail.com
License: UNKNOWN
Platform: UNKNOWN
Classifier: Programming Language :: Python :: 3
Classifier: License :: OSI Approved :: MIT License
Classifier: Operating System :: OS Independent
Requires-Python: >=3.6
Requires-Dist: requests
Requires-Dist: openpyxl
Requires-Dist: mysql-connector-python
Requires-Dist: python-dateutil
